{
  "users": {
    "6285764218011@s.whatsapp.net": {
      "afkTime": -1,
      "afkReason": "",
      "limit": 10
    },
    "6285880814606@s.whatsapp.net": {
      "afkTime": -1,
      "afkReason": "",
      "limit": 10
    },
    "6281268854288@s.whatsapp.net": {
      "afkTime": -1,
      "afkReason": "",
      "limit": 10
    },
    "6282211165417@s.whatsapp.net": {
      "afkTime": -1,
      "afkReason": "",
      "limit": 8
    },
    "62895397918020@s.whatsapp.net": {
      "afkTime": -1,
      "afkReason": "",
      "limit": "Infinity"
    },
    "6285839042790@s.whatsapp.net": {
      "afkTime": -1,
      "afkReason": "",
      "limit": 10
    },
    "6281276449950@s.whatsapp.net": {
      "afkTime": -1,
      "afkReason": "",
      "limit": 10
    },
    "62895635752558@s.whatsapp.net": {
      "afkTime": -1,
      "afkReason": "",
      "limit": 10
    },
    "6285713544055@s.whatsapp.net": {
      "afkTime": -1,
      "afkReason": "",
      "limit": 10
    },
    "6283163327880@s.whatsapp.net": {
      "afkTime": -1,
      "afkReason": "",
      "limit": 10
    },
    "6285724404318@s.whatsapp.net": {
      "afkTime": -1,
      "afkReason": "",
      "limit": -18
    },
    "6285774612265@s.whatsapp.net": {
      "afkTime": -1,
      "afkReason": "",
      "limit": 10
    },
    "62882019402301@s.whatsapp.net": {
      "afkTime": -1,
      "afkReason": "",
      "limit": 10
    },
    "6285707742304@s.whatsapp.net": {
      "afkTime": -1,
      "afkReason": "",
      "limit": 10
    },
    "60179098419@s.whatsapp.net": {
      "afkTime": -1,
      "afkReason": "",
      "limit": 10
    },
    "6281513570023@s.whatsapp.net": {
      "afkTime": -1,
      "afkReason": "",
      "limit": 10
    },
    "6281327496283@s.whatsapp.net": {
      "afkTime": -1,
      "afkReason": "",
      "limit": "Infinity"
    },
    "6289510530396@s.whatsapp.net": {
      "afkTime": -1,
      "afkReason": "",
      "limit": 10
    },
    "6282399255216@s.whatsapp.net": {
      "afkTime": -1,
      "afkReason": "",
      "limit": 10
    },
    "6289503316727@s.whatsapp.net": {
      "afkTime": -1,
      "afkReason": "",
      "limit": 10
    },
    "6282150964792@s.whatsapp.net": {
      "afkTime": -1,
      "afkReason": "",
      "limit": 10
    },
    "6285642159032@s.whatsapp.net": {
      "afkTime": -1,
      "afkReason": "",
      "limit": "Infinity"
    },
    "6285759155706@s.whatsapp.net": {
      "afkTime": -1,
      "afkReason": "",
      "limit": 10
    },
    "6287742293243@s.whatsapp.net": {
      "afkTime": -1,
      "afkReason": "",
      "limit": 10
    },
    "6289504067405@s.whatsapp.net": {
      "afkTime": -1,
      "afkReason": "",
      "limit": 10
    },
    "62895401373165@s.whatsapp.net": {
      "afkTime": -1,
      "afkReason": "",
      "limit": "Infinity"
    },
    "6285798044025@s.whatsapp.net": {
      "afkTime": -1,
      "afkReason": "",
      "limit": 10
    },
    "6283863370841@s.whatsapp.net": {
      "afkTime": -1,
      "afkReason": "",
      "limit": 10
    },
    "6283157750568@s.whatsapp.net": {
      "afkTime": -1,
      "afkReason": "",
      "limit": "Infinity"
    },
    "6287751872835@s.whatsapp.net": {
      "afkTime": -1,
      "afkReason": "",
      "limit": 10
    },
    "6289523321769@s.whatsapp.net": {
      "afkTime": -1,
      "afkReason": "",
      "limit": 10
    },
    "628816277148@s.whatsapp.net": {
      "afkTime": -1,
      "afkReason": "",
      "limit": 8
    },
    "628988885167@s.whatsapp.net": {
      "afkTime": -1,
      "afkReason": "",
      "limit": 10
    },
    "6288293100476@s.whatsapp.net": {
      "afkTime": -1,
      "afkReason": "",
      "limit": 10
    },
    "6285867691103@s.whatsapp.net": {
      "afkTime": -1,
      "afkReason": "",
      "limit": 8
    },
    "6281996162611@s.whatsapp.net": {
      "afkTime": -1,
      "afkReason": "",
      "limit": 10
    },
    "6289688359417@s.whatsapp.net": {
      "afkTime": -1,
      "afkReason": "",
      "limit": 10
    },
    "6282347929043@s.whatsapp.net": {
      "afkTime": -1,
      "afkReason": "",
      "limit": 10
    },
    "6285694832830@s.whatsapp.net": {
      "afkTime": -1,
      "afkReason": "",
      "limit": 8
    },
    "6281528986980@s.whatsapp.net": {
      "afkTime": -1,
      "afkReason": "",
      "limit": 10
    },
    "6285877529824@s.whatsapp.net": {
      "afkTime": -1,
      "afkReason": "",
      "limit": 8
    },
    "6283844865857@s.whatsapp.net": {
      "afkTime": -1,
      "afkReason": "",
      "limit": 10
    },
    "628819896125@s.whatsapp.net": {
      "afkTime": -1,
      "afkReason": "",
      "limit": 10
    },
    "6285732131774@s.whatsapp.net": {
      "afkTime": -1,
      "afkReason": "",
      "limit": 10
    },
    "6282161421761@s.whatsapp.net": {
      "afkTime": -1,
      "afkReason": "",
      "limit": 10
    },
    "6285727594435@s.whatsapp.net": {
      "afkTime": -1,
      "afkReason": "",
      "limit": 10
    },
    "6285828984453@s.whatsapp.net": {
      "afkTime": -1,
      "afkReason": "",
      "limit": 10
    },
    "6281218500871@s.whatsapp.net": {
      "afkTime": -1,
      "afkReason": "",
      "limit": 10
    },
    "6288295081199@s.whatsapp.net": {
      "afkTime": -1,
      "afkReason": "",
      "limit": 10
    },
    "6282130761029@s.whatsapp.net": {
      "afkTime": -1,
      "afkReason": "",
      "limit": 10
    },
    "6288221411060@s.whatsapp.net": {
      "afkTime": -1,
      "afkReason": "",
      "limit": 10
    },
    "60142716632@s.whatsapp.net": {
      "afkTime": -1,
      "afkReason": "",
      "limit": 10
    },
    "6281334162242@s.whatsapp.net": {
      "afkTime": -1,
      "afkReason": "",
      "limit": 10
    },
    "6281515047514@s.whatsapp.net": {
      "afkTime": -1,
      "afkReason": "",
      "limit": 10
    },
    "6288225994170@s.whatsapp.net": {
      "afkTime": -1,
      "afkReason": "",
      "limit": 10
    },
    "6282262257676@s.whatsapp.net": {
      "afkTime": -1,
      "afkReason": "",
      "limit": 10
    },
    "6282317614213@s.whatsapp.net": {
      "afkTime": -1,
      "afkReason": "",
      "limit": 10
    },
    "6285848460519@s.whatsapp.net": {
      "afkTime": -1,
      "afkReason": "",
      "limit": 8
    },
    "6285828543470@s.whatsapp.net": {
      "afkTime": -1,
      "afkReason": "",
      "limit": 10
    },
    "6285707403746@s.whatsapp.net": {
      "afkTime": -1,
      "afkReason": "",
      "limit": 10
    },
    "6283128425769@s.whatsapp.net": {
      "afkTime": -1,
      "afkReason": "",
      "limit": 10
    },
    "6283823303164@s.whatsapp.net": {
      "afkTime": -1,
      "afkReason": "",
      "limit": 10
    },
    "6282285426462@s.whatsapp.net": {
      "afkTime": -1,
      "afkReason": "",
      "limit": 10
    },
    "6289531587536@s.whatsapp.net": {
      "afkTime": -1,
      "afkReason": "",
      "limit": 10
    },
    "62882019702458@s.whatsapp.net": {
      "afkTime": -1,
      "afkReason": "",
      "limit": 10
    },
    "6289638647489@s.whatsapp.net": {
      "afkTime": -1,
      "afkReason": "",
      "limit": 10
    },
    "6283134144967@s.whatsapp.net": {
      "afkTime": -1,
      "afkReason": "",
      "limit": 10
    },
    "6285231651905@s.whatsapp.net": {
      "afkTime": -1,
      "afkReason": "",
      "limit": 10
    },
    "6281327889654@s.whatsapp.net": {
      "afkTime": -1,
      "afkReason": "",
      "limit": 8
    },
    "6281572044030@s.whatsapp.net": {
      "afkTime": -1,
      "afkReason": "",
      "limit": 10
    },
    "6285880427503@s.whatsapp.net": {
      "afkTime": -1,
      "afkReason": "",
      "limit": 10
    },
    "6288980068100@s.whatsapp.net": {
      "afkTime": -1,
      "afkReason": "",
      "limit": 10
    },
    "6281211421187@s.whatsapp.net": {
      "afkTime": -1,
      "afkReason": "",
      "limit": 10
    },
    "6282134327579@s.whatsapp.net": {
      "afkTime": -1,
      "afkReason": "",
      "limit": 10
    },
    "6281250849703@s.whatsapp.net": {
      "afkTime": -1,
      "afkReason": "",
      "limit": 10
    },
    "6285840955818@s.whatsapp.net": {
      "afkTime": -1,
      "afkReason": "",
      "limit": 10
    },
    "6282347958972@s.whatsapp.net": {
      "afkTime": -1,
      "afkReason": "",
      "limit": 10
    },
    "6282113973295@s.whatsapp.net": {
      "afkTime": -1,
      "afkReason": "",
      "limit": 10
    },
    "6281461204858@s.whatsapp.net": {
      "afkTime": -1,
      "afkReason": "",
      "limit": 10
    },
    "6281215438573@s.whatsapp.net": {
      "afkTime": -1,
      "afkReason": "",
      "limit": 10
    },
    "6285876200516@s.whatsapp.net": {
      "afkTime": -1,
      "afkReason": "",
      "limit": 10
    },
    "6281250303130@s.whatsapp.net": {
      "afkTime": -1,
      "afkReason": "",
      "limit": 10
    },
    "60133359853@s.whatsapp.net": {
      "afkTime": -1,
      "afkReason": "",
      "limit": 10
    },
    "6285783346157@s.whatsapp.net": {
      "afkTime": -1,
      "afkReason": "",
      "limit": 10
    },
    "6285783277684@s.whatsapp.net": {
      "afkTime": -1,
      "afkReason": "",
      "limit": 10
    },
    "6289529452953@s.whatsapp.net": {
      "afkTime": -1,
      "afkReason": "",
      "limit": 10
    },
    "6282282864304@s.whatsapp.net": {
      "afkTime": -1,
      "afkReason": "",
      "limit": 10
    },
    "6281929828525@s.whatsapp.net": {
      "afkTime": -1,
      "afkReason": "",
      "limit": 6
    },
    "6281237272241@s.whatsapp.net": {
      "afkTime": -1,
      "afkReason": "",
      "limit": 10
    },
    "6289619598060@s.whatsapp.net": {
      "afkTime": -1,
      "afkReason": "",
      "limit": 10
    },
    "60137012582@s.whatsapp.net": {
      "afkTime": -1,
      "afkReason": "",
      "limit": 10
    },
    "6281227160607@s.whatsapp.net": {
      "afkTime": -1,
      "afkReason": "",
      "limit": 10
    },
    "6287762572515@s.whatsapp.net": {
      "afkTime": -1,
      "afkReason": "",
      "limit": 8
    },
    "6285705714232@s.whatsapp.net": {
      "afkTime": -1,
      "afkReason": "",
      "limit": 10
    },
    "6285825107524@s.whatsapp.net": {
      "afkTime": -1,
      "afkReason": "",
      "limit": 10
    },
    "6288227894199@s.whatsapp.net": {
      "afkTime": -1,
      "afkReason": "",
      "limit": 10
    },
    "6289522984639@s.whatsapp.net": {
      "afkTime": -1,
      "afkReason": "",
      "limit": 10
    },
    "6285745166125@s.whatsapp.net": {
      "afkTime": -1,
      "afkReason": "",
      "limit": 10
    },
    "6283848573579@s.whatsapp.net": {
      "afkTime": -1,
      "afkReason": "",
      "limit": 10
    },
    "62895326098667@s.whatsapp.net": {
      "afkTime": -1,
      "afkReason": "",
      "limit": 10
    },
    "6285787088329@s.whatsapp.net": {
      "afkTime": -1,
      "afkReason": "",
      "limit": 10
    },
    "6283845383481@s.whatsapp.net": {
      "afkTime": -1,
      "afkReason": "",
      "limit": 10
    },
    "6285654648428@s.whatsapp.net": {
      "afkTime": -1,
      "afkReason": "",
      "limit": 10
    },
    "6282117772562@s.whatsapp.net": {
      "afkTime": -1,
      "afkReason": "",
      "limit": 10
    },
    "6282111028735@s.whatsapp.net": {
      "afkTime": -1,
      "afkReason": "",
      "limit": 10
    },
    "6285846542436@s.whatsapp.net": {
      "afkTime": -1,
      "afkReason": "",
      "limit": 10
    },
    "6281247936112@s.whatsapp.net": {
      "afkTime": -1,
      "afkReason": "",
      "limit": 10
    },
    "6281251206167@s.whatsapp.net": {
      "afkTime": -1,
      "afkReason": "",
      "limit": 10
    },
    "6285777849025@s.whatsapp.net": {
      "afkTime": -1,
      "afkReason": "",
      "limit": 10
    },
    "6283167460871@s.whatsapp.net": {
      "afkTime": -1,
      "afkReason": "",
      "limit": 10
    },
    "6285850437286@s.whatsapp.net": {
      "afkTime": -1,
      "afkReason": "",
      "limit": 10
    },
    "6281316510126@s.whatsapp.net": {
      "afkTime": -1,
      "afkReason": "",
      "limit": 10
    },
    "6285971891700@s.whatsapp.net": {
      "afkTime": -1,
      "afkReason": "",
      "limit": 10
    },
    "6285920656467@s.whatsapp.net": {
      "afkTime": -1,
      "afkReason": "",
      "limit": 10
    },
    "6289647265012@s.whatsapp.net": {
      "afkTime": -1,
      "afkReason": "",
      "limit": 10
    },
    "6281360446336@s.whatsapp.net": {
      "afkTime": -1,
      "afkReason": "",
      "limit": 10
    },
    "6285813664687@s.whatsapp.net": {
      "afkTime": -1,
      "afkReason": "",
      "limit": 10
    },
    "6281362262051@s.whatsapp.net": {
      "afkTime": -1,
      "afkReason": "",
      "limit": 10
    },
    "6287727215675@s.whatsapp.net": {
      "afkTime": -1,
      "afkReason": "",
      "limit": 10
    },
    "6289652371715@s.whatsapp.net": {
      "afkTime": -1,
      "afkReason": "",
      "limit": 10
    },
    "6281385738120@s.whatsapp.net": {
      "afkTime": -1,
      "afkReason": "",
      "limit": 10
    },
    "6288216480090@s.whatsapp.net": {
      "afkTime": -1,
      "afkReason": "",
      "limit": 10
    },
    "6289518445259@s.whatsapp.net": {
      "afkTime": -1,
      "afkReason": "",
      "limit": 10
    },
    "6289654489730@s.whatsapp.net": {
      "afkTime": -1,
      "afkReason": "",
      "limit": 10
    },
    "6283180501538@s.whatsapp.net": {
      "afkTime": -1,
      "afkReason": "",
      "limit": 10
    },
    "6289524584329@s.whatsapp.net": {
      "afkTime": -1,
      "afkReason": "",
      "limit": 10
    },
    "6289666492015@s.whatsapp.net": {
      "afkTime": -1,
      "afkReason": "",
      "limit": 10
    },
    "6289509071671@s.whatsapp.net": {
      "afkTime": -1,
      "afkReason": "",
      "limit": 10
    },
    "6281779423186@s.whatsapp.net": {
      "afkTime": -1,
      "afkReason": "",
      "limit": 10
    },
    "6281394931875@s.whatsapp.net": {
      "afkTime": -1,
      "afkReason": "",
      "limit": 10
    },
    "6285256092614@s.whatsapp.net": {
      "afkTime": -1,
      "afkReason": "",
      "limit": 10
    },
    "6281260595770@s.whatsapp.net": {
      "afkTime": -1,
      "afkReason": "",
      "limit": 10
    },
    "6281340040296@s.whatsapp.net": {
      "afkTime": -1,
      "afkReason": "",
      "limit": 10
    },
    "6287802093176@s.whatsapp.net": {
      "afkTime": -1,
      "afkReason": "",
      "limit": 10
    },
    "62881025716277@s.whatsapp.net": {
      "afkTime": -1,
      "afkReason": "",
      "limit": 10
    },
    "6281278600878@s.whatsapp.net": {
      "afkTime": -1,
      "afkReason": "",
      "limit": 10
    },
    "628818182312@s.whatsapp.net": {
      "afkTime": -1,
      "afkReason": "",
      "limit": 10
    },
    "6289623346629@s.whatsapp.net": {
      "afkTime": -1,
      "afkReason": "",
      "limit": 10
    },
    "6281914026158@s.whatsapp.net": {
      "afkTime": -1,
      "afkReason": "",
      "limit": "Infinity"
    },
    "6283832460584@s.whatsapp.net": {
      "afkTime": -1,
      "afkReason": "",
      "limit": "Infinity"
    },
    "6281937576780@s.whatsapp.net": {
      "afkTime": -1,
      "afkReason": "",
      "limit": 10
    },
    "6281322659303@s.whatsapp.net": {
      "afkTime": -1,
      "afkReason": "",
      "limit": 10
    }
  },
  "chats": {
    "120363040241265344@g.us": {
      "mute": false,
      "antilink": false
    },
    "62895397918020@s.whatsapp.net": {
      "mute": false,
      "antilink": false
    },
    "6285724404318@s.whatsapp.net": {
      "mute": false,
      "antilink": false
    },
    "120363041242208535@g.us": {
      "mute": false,
      "antilink": false
    },
    "6281327496283@s.whatsapp.net": {
      "mute": false,
      "antilink": false
    },
    "201287864167-1507744804@g.us": {
      "mute": false,
      "antilink": false
    },
    "6287742293243@s.whatsapp.net": {
      "mute": false,
      "antilink": false
    },
    "6289504067405@s.whatsapp.net": {
      "mute": false,
      "antilink": false
    },
    "62895401373165@s.whatsapp.net": {
      "mute": false,
      "antilink": false
    },
    "6283157750564-1635131253@g.us": {
      "mute": false,
      "antilink": false
    },
    "120363022776718251@g.us": {
      "mute": false,
      "antilink": false
    },
    "6285694832830@s.whatsapp.net": {
      "mute": false,
      "antilink": false
    },
    "120363022518002549@g.us": {
      "mute": false,
      "antilink": false
    },
    "120363024503380794@g.us": {
      "mute": false,
      "antilink": false
    },
    "6287705048235@s.whatsapp.net": {
      "mute": false,
      "antilink": false
    },
    "120363025751646545@g.us": {
      "mute": false,
      "antilink": false
    },
    "120363041639976908@g.us": {
      "mute": false,
      "antilink": false
    },
    "120363023503027932@g.us": {
      "mute": false,
      "antilink": false
    },
    "120363022873201166@g.us": {
      "mute": false,
      "antilink": false
    },
    "6285642159032@s.whatsapp.net": {
      "mute": false,
      "antilink": false
    },
    "120363040954290088@g.us": {
      "mute": false,
      "antilink": false
    },
    "6285876102845-1625891381@g.us": {
      "mute": false,
      "antilink": false
    },
    "120363042304052058@g.us": {
      "mute": false,
      "antilink": false
    },
    "120363025641317889@g.us": {
      "mute": false,
      "antilink": false
    },
    "120363038958575910@g.us": {
      "mute": false,
      "antilink": false
    },
    "6283178502766@s.whatsapp.net": {
      "mute": false,
      "antilink": false
    },
    "6281914026158@s.whatsapp.net": {
      "mute": false,
      "antilink": false
    },
    "62881025716277@s.whatsapp.net": {
      "mute": false,
      "antilink": false
    },
    "919043441960@s.whatsapp.net": {
      "mute": false,
      "antilink": false
    },
    "120363026814584754@g.us": {
      "mute": false,
      "antilink": false
    },
    "6281937576780@s.whatsapp.net": {
      "mute": false,
      "antilink": false
    },
    "6283832460584@s.whatsapp.net": {
      "mute": false,
      "antilink": false
    },
    "6289657756988-1635331439@g.us": {
      "mute": false,
      "antilink": false
    }
  },
  "database": {},
  "game": {
    "tebaklagu": [],
    "family100": [],
    "math": [],
    "tebakgambar": [],
    "tebakkata": [],
    "lontong": [],
    "lontong_desk": [],
    "kalimat": [],
    "lirik": [],
    "tebakan": []
  },
  "settings": {
    "6281914026158@s.whatsapp.net": {
      "status": 0,
      "autobio": false,
      "templateImage": true,
      "templateVideo": false,
      "templateGif": false,
      "templateMsg": false
    },
    "6285642159032@s.whatsapp.net": {
      "status": 0,
      "autobio": false,
      "templateImage": true,
      "templateVideo": false,
      "templateGif": false,
      "templateMsg": false
    },
    "6281327496283@s.whatsapp.net": {
      "status": 0,
      "autobio": false,
      "templateImage": true,
      "templateVideo": false,
      "templateGif": false,
      "templateMsg": false
    },
    "62895397918020@s.whatsapp.net": {
      "status": 0,
      "autobio": false,
      "templateImage": true,
      "templateVideo": false,
      "templateGif": false,
      "templateMsg": false
    },
    "6283832460584@s.whatsapp.net": {
      "status": 0,
      "autobio": false,
      "templateImage": true,
      "templateVideo": false,
      "templateGif": false,
      "templateMsg": false
    }
  },
  "others": {
    "vote": []
  },
  "sticker": {}
}